{
    "additionalProperties": true,
    "description": "Abbildung eines Tarifs mit regionaler Zuordnung von Preisen und Auf- und Abschlägen.\n\n.. raw:: html\n\n    <object data=\"../_static/images/bo4e/bo/Regionaltarif.svg\" type=\"image/svg+xml\"></object>\n\n.. HINT::\n    `Regionaltarif JSON Schema <https://json-schema.app/view/%23?url=https://raw.githubusercontent.com/BO4E/BO4E-Schemas/{__gh_version__}/src/bo4e_schemas/bo/Regionaltarif.json>`_",
    "properties": {
        "_id": {
            "anyOf": [
                {
                    "type": "string"
                },
                {
                    "type": "null"
                }
            ],
            "default": null,
            "description": "Eine generische ID, die für eigene Zwecke genutzt werden kann.\nZ.B. könnten hier UUIDs aus einer Datenbank stehen oder URLs zu einem Backend-System.",
            "title": " Id"
        },
        "_typ": {
            "const": "REGIONALTARIF",
            "default": "REGIONALTARIF",
            "enum": [
                "REGIONALTARIF"
            ],
            "title": " Typ",
            "type": "string"
        },
        "_version": {
            "anyOf": [
                {
                    "type": "string"
                },
                {
                    "type": "null"
                }
            ],
            "default": "202501.0.0",
            "description": "Version der BO-Struktur aka \"fachliche Versionierung\"",
            "title": " Version"
        },
        "anbieter": {
            "anyOf": [
                {
                    "$ref": "https://raw.githubusercontent.com/BO4E/BO4E-Schemas/v202501.0.0/src/bo4e_schemas/bo/Marktteilnehmer.json"
                },
                {
                    "type": "null"
                }
            ],
            "default": null,
            "description": "Der Marktteilnehmer (Lieferant), der diesen Tarif anbietet"
        },
        "anbietername": {
            "anyOf": [
                {
                    "type": "string"
                },
                {
                    "type": "null"
                }
            ],
            "default": null,
            "description": "Der Name des Marktpartners, der den Tarif anbietet",
            "title": "Anbietername"
        },
        "anwendungVon": {
            "anyOf": [
                {
                    "format": "date-time",
                    "type": "string"
                },
                {
                    "type": "null"
                }
            ],
            "default": null,
            "description": "Angabe des inklusiven Zeitpunkts, ab dem der Tarif bzw. der Preis angewendet und abgerechnet wird,\nz.B. \"2021-07-20T18:31:48Z\"",
            "title": "Anwendungvon"
        },
        "bemerkung": {
            "anyOf": [
                {
                    "type": "string"
                },
                {
                    "type": "null"
                }
            ],
            "default": null,
            "description": "Freitext",
            "title": "Bemerkung"
        },
        "berechnungsparameter": {
            "anyOf": [
                {
                    "$ref": "https://raw.githubusercontent.com/BO4E/BO4E-Schemas/v202501.0.0/src/bo4e_schemas/com/Tarifberechnungsparameter.json"
                },
                {
                    "type": "null"
                }
            ],
            "default": null,
            "description": "Für die Berechnung der Kosten sind die hier abgebildeten Parameter heranzuziehen"
        },
        "bezeichnung": {
            "anyOf": [
                {
                    "type": "string"
                },
                {
                    "type": "null"
                }
            ],
            "default": null,
            "description": "Name des Tarifs",
            "title": "Bezeichnung"
        },
        "energiemix": {
            "anyOf": [
                {
                    "$ref": "https://raw.githubusercontent.com/BO4E/BO4E-Schemas/v202501.0.0/src/bo4e_schemas/com/Energiemix.json"
                },
                {
                    "type": "null"
                }
            ],
            "default": null,
            "description": "Der Energiemix, der für diesen Tarif gilt"
        },
        "kundentypen": {
            "anyOf": [
                {
                    "items": {
                        "$ref": "https://raw.githubusercontent.com/BO4E/BO4E-Schemas/v202501.0.0/src/bo4e_schemas/enum/Kundentyp.json"
                    },
                    "type": "array"
                },
                {
                    "type": "null"
                }
            ],
            "default": null,
            "description": "Kundentypen für den der Tarif gilt, z.B. Privatkunden",
            "title": "Kundentypen"
        },
        "preisgarantien": {
            "anyOf": [
                {
                    "items": {
                        "$ref": "https://raw.githubusercontent.com/BO4E/BO4E-Schemas/v202501.0.0/src/bo4e_schemas/com/RegionalePreisgarantie.json"
                    },
                    "type": "array"
                },
                {
                    "type": "null"
                }
            ],
            "default": null,
            "description": "Festlegung von Garantien für bestimmte Preisanteile",
            "title": "Preisgarantien"
        },
        "preisstand": {
            "anyOf": [
                {
                    "format": "date-time",
                    "type": "string"
                },
                {
                    "type": "null"
                }
            ],
            "default": null,
            "description": "Gibt an, wann der Preis zuletzt angepasst wurde",
            "title": "Preisstand"
        },
        "registeranzahl": {
            "anyOf": [
                {
                    "$ref": "https://raw.githubusercontent.com/BO4E/BO4E-Schemas/v202501.0.0/src/bo4e_schemas/enum/Registeranzahl.json"
                },
                {
                    "type": "null"
                }
            ],
            "default": null,
            "description": "Die Art des Tarifes, z.B. Eintarif oder Mehrtarif"
        },
        "sparte": {
            "anyOf": [
                {
                    "$ref": "https://raw.githubusercontent.com/BO4E/BO4E-Schemas/v202501.0.0/src/bo4e_schemas/enum/Sparte.json"
                },
                {
                    "type": "null"
                }
            ],
            "default": null,
            "description": "Strom oder Gas, etc."
        },
        "tarifAufAbschlaege": {
            "anyOf": [
                {
                    "items": {
                        "$ref": "https://raw.githubusercontent.com/BO4E/BO4E-Schemas/v202501.0.0/src/bo4e_schemas/com/RegionalerAufAbschlag.json"
                    },
                    "type": "array"
                },
                {
                    "type": "null"
                }
            ],
            "default": null,
            "description": "Auf- und Abschläge auf die Preise oder Kosten mit regionaler Eingrenzung",
            "title": "Tarifaufabschlaege"
        },
        "tarifeinschraenkung": {
            "anyOf": [
                {
                    "$ref": "https://raw.githubusercontent.com/BO4E/BO4E-Schemas/v202501.0.0/src/bo4e_schemas/com/Tarifeinschraenkung.json"
                },
                {
                    "type": "null"
                }
            ],
            "default": null,
            "description": "Die Bedingungen und Einschränkungen unter denen ein Tarif angewendet werden kann"
        },
        "tarifmerkmale": {
            "anyOf": [
                {
                    "items": {
                        "$ref": "https://raw.githubusercontent.com/BO4E/BO4E-Schemas/v202501.0.0/src/bo4e_schemas/enum/Tarifmerkmal.json"
                    },
                    "type": "array"
                },
                {
                    "type": "null"
                }
            ],
            "default": null,
            "description": "Weitere Merkmale des Tarifs, z.B. Festpreis oder Vorkasse",
            "title": "Tarifmerkmale"
        },
        "tarifpreise": {
            "anyOf": [
                {
                    "items": {
                        "$ref": "https://raw.githubusercontent.com/BO4E/BO4E-Schemas/v202501.0.0/src/bo4e_schemas/com/RegionaleTarifpreisposition.json"
                    },
                    "type": "array"
                },
                {
                    "type": "null"
                }
            ],
            "default": null,
            "description": "Die festgelegten Preise mit regionaler Eingrenzung, z.B. für Arbeitspreis, Grundpreis etc.",
            "title": "Tarifpreise"
        },
        "tariftyp": {
            "anyOf": [
                {
                    "$ref": "https://raw.githubusercontent.com/BO4E/BO4E-Schemas/v202501.0.0/src/bo4e_schemas/enum/Tariftyp.json"
                },
                {
                    "type": "null"
                }
            ],
            "default": null,
            "description": "Hinweis auf den Tariftyp, z.B. Grundversorgung oder Sondertarif"
        },
        "vertragskonditionen": {
            "anyOf": [
                {
                    "$ref": "https://raw.githubusercontent.com/BO4E/BO4E-Schemas/v202501.0.0/src/bo4e_schemas/com/Vertragskonditionen.json"
                },
                {
                    "type": "null"
                }
            ],
            "default": null,
            "description": "Mindestlaufzeiten und Kündigungsfristen zusammengefasst"
        },
        "website": {
            "anyOf": [
                {
                    "type": "string"
                },
                {
                    "type": "null"
                }
            ],
            "default": null,
            "description": "Internetseite auf dem der Tarif zu finden ist",
            "title": "Website"
        },
        "zeitlicheGueltigkeit": {
            "anyOf": [
                {
                    "$ref": "https://raw.githubusercontent.com/BO4E/BO4E-Schemas/v202501.0.0/src/bo4e_schemas/com/Zeitraum.json"
                },
                {
                    "type": "null"
                }
            ],
            "default": null,
            "description": "Angabe, in welchem Zeitraum der Tarif gültig ist"
        },
        "zusatzAttribute": {
            "anyOf": [
                {
                    "items": {
                        "$ref": "https://raw.githubusercontent.com/BO4E/BO4E-Schemas/v202501.0.0/src/bo4e_schemas/ZusatzAttribut.json"
                    },
                    "type": "array"
                },
                {
                    "type": "null"
                }
            ],
            "default": null,
            "title": "Zusatzattribute"
        }
    },
    "title": "Regionaltarif",
    "type": "object"
}
